labnas/__init__.py
labnas/local/__init__.py
labnas/local/base.py
labnas/local/files.py
labnas/local/log.py
labnas/local/storage.py
labnas/remote/__init__.py
labnas/remote/auto_dset/daq.py
labnas/remote/auto_dset/database.py
labnas/remote/auto_dset/eyetracking.py
labnas/remote/auto_dset/metadata.py
labnas/remote/auto_dset/raw_stim.py
labnas/remote/auto_dset/stim.py
labnas/remote/auto_dset/suite2p.py
labnas/remote/auto_dset/utils.py
labnas/remote/base.py
labnas/remote/imaging.py
labnas/remote/utils.py
labnas-0.2.8.dist-info/METADATA
labnas-0.2.8.dist-info/WHEEL
labnas-0.2.8.dist-info/RECORD
