Metadata-Version: 2.1
Name: labnas
Version: 0.2.8
Summary: 
Author: Mathis
Author-email: mathis.bassler@protonmail.com
Requires-Python: >=3.10,<4.0
Classifier: Programming Language :: Python :: 3
Classifier: Programming Language :: Python :: 3.10
Classifier: Programming Language :: Python :: 3.11
Requires-Dist: pandas (>=2.0.1,<3.0.0)
Requires-Dist: pysftp (>=0.2.9,<0.3.0)
Requires-Dist: tifffile (>=2023.2.3,<2024.0.0)
Requires-Dist: tqdm (>=4.64.1,<5.0.0)
Requires-Dist: zarr (>=2.16.1,<3.0.0)
